namesfr/__init__.py
namesfr/dist.all.last
namesfr/dist.female.first
namesfr/dist.male.first
namesfr/main.py
namesfr-0.0.2.dist-info/METADATA
namesfr-0.0.2.dist-info/WHEEL
namesfr-0.0.2.dist-info/licenses/AUTHORS.rst
namesfr-0.0.2.dist-info/licenses/LICENSE.txt
namesfr-0.0.2.dist-info/RECORD
