Metadata-Version: 2.1
Name: namesfr
Version: 0.0.2
Summary: Random french name generator
Project-URL: Homepage, https://github.com/Sethnico/namesfr
Project-URL: Bug Tracker, https://github.com/Sethnico/namesfr/issues
Author: Nicolas Renard
License-File: AUTHORS.rst
License-File: LICENSE.txt
Classifier: License :: OSI Approved :: MIT License
Classifier: Operating System :: OS Independent
Classifier: Programming Language :: Python :: 3
Requires-Python: >=3.7
